passwordler/__init__.py
passwordler/_internals.py
passwordler/decrypt_password.py
passwordler/encrypt_password.py
passwordler/generate_password.py
passwordler/password_strength.py
passwordler-2.1.3.dist-info/LICENSE
passwordler-2.1.3.dist-info/METADATA
passwordler-2.1.3.dist-info/WHEEL
passwordler-2.1.3.dist-info/RECORD
