Metadata-Version: 2.1
Name: passwordler
Version: 2.1.3
Summary: A simple utility package for passwords
License: MIT
Author: Kiersten Gilberg, Michelle Hunn, Rory White, Yiwei Zhang
Requires-Python: >=3.11,<4.0
Classifier: License :: OSI Approved :: MIT License
Classifier: Programming Language :: Python :: 3
Classifier: Programming Language :: Python :: 3.11
Classifier: Programming Language :: Python :: 3.12
